README.txt
setup.cfg
setup.py
src/jcrack/__init__.py
src/jcrack/celeryconfig.py
src/jcrack/crackchars.py
src/jcrack/hashcattypes.py
src/jcrack/jconfig.py
src/jcrack/jcrack.py
src/jcrack.egg-info/PKG-INFO
src/jcrack.egg-info/SOURCES.txt
src/jcrack.egg-info/dependency_links.txt
src/jcrack.egg-info/requires.txt
src/jcrack.egg-info/top_level.txt