Metadata-Version: 1.0
Name: jcrack
Version: 0.0.2
Summary: Jabbercracky: A Hash-Cracking Web Service
Home-page: http://awgh.org
Author: awgh
Author-email: awgh@awgh.org
License: GPL
Keywords: hash crack md5 lm ntlm jabbercracky jcrack
Platform: UNKNOWN
Classifier: Programming Language :: Python
Classifier: Operating System :: POSIX
Classifier: Development Status :: 2 - Pre-Alpha
Classifier: Topic :: Security :: Cryptography
Classifier: Topic :: Internet :: WWW/HTTP
